<?xml version="1.0" encoding="utf-8"?>

<!--
@package      hubzero-cms
@copyright    Copyright (c) 2005-2020 The Regents of the University of California.
@license      http://opensource.org/licenses/MIT MIT
-->

<metadata>
	<layout title="Resource (series) Layout">
		<message>
			<![CDATA[Resource (series) Layout]]>
		</message>
	</layout>
	<!-- Add fields to the request variables for the layout. -->
	<fields name="request">
		<fieldset name="request">
			<field name="id" type="text" label="Resource ID" description="Enter the ID of a Resource to view" />
		</fieldset>
	</fields>
</metadata>